src/__init__.py
src/states.py
COVIDDataInterface-0.0.1.dist-info/METADATA
COVIDDataInterface-0.0.1.dist-info/WHEEL
COVIDDataInterface-0.0.1.dist-info/top_level.txt
COVIDDataInterface-0.0.1.dist-info/RECORD
