Metadata-Version: 2.1
Name: COVIDDataInterface
Version: 0.0.1
Summary: Package to Access State COVID Data
Home-page: https://github.com/pypa/sampleproject
Author: Devon Schwartz and Neil Aylor
Author-email: <devon.s.schwartz@gmail.com>
License: UNKNOWN
Project-URL: Bug Tracker, https://github.com/pypa/sampleproject/issues
Keywords: python,COVID,state
Platform: UNKNOWN
Classifier: Development Status :: 3 - Alpha
Classifier: Intended Audience :: Education
Classifier: Programming Language :: Python :: 2
Classifier: Programming Language :: Python :: 3
Classifier: Operating System :: MacOS :: MacOS X
Classifier: Operating System :: Microsoft :: Windows
Requires-Dist: pandas
